Workbook

Sheet Inputs
A1: ASSETS | B1: Amount ($m)
A2: Cash | B2: 500
A3: Central Bank Reserves | B3: 200
A4: Government Bonds | B4: 300
A5: AAA Corporate Bonds | B5: 200
A6: BB Corporate Bonds | B6: 100
A7: Home Loans | B7: 2000
A8: Corporate Loans | B8: 800
A10: LIABILITIES & CAPITAL
A11: Retail Deposits (Stable) | B11: 1000
A12: Retail Deposits (Less Stable) | B12: 500
A13: Wholesale Funding (<30 days) | B13: 400
A14: Interbank Loans (<30 days) | B14: 200
A15: Equity / Tier 1 Capital | B15: 600
A16: Wholesale Funding (>1 year) | B16: 300

Sheet LCR
A1: HQLA (High Quality Liquid Assets)
A2: Asset | B2: Amount | C2: Haircut | D2: HQLA Value
A3: Cash | B3: =Inputs!B2 -> 500 | C3: 0 | D3: =B3*(1-C3) -> 500
A4: Central Bank Reserves | B4: =Inputs!B3 -> 200 | C4: 0 | D4: =B4*(1-C4) -> 200
A5: Government Bonds | B5: =Inputs!B4 -> 300 | C5: 0 | D5: =B5*(1-C5) -> 300
A6: AAA Corporate Bonds | B6: =Inputs!B5 -> 200 | C6: 0.15 | D6: =B6*(1-C6) -> 170
A7: BB Corporate Bonds | B7: =Inputs!B6 -> 100 | C7: 0.5 | D7: =B7*(1-C7) -> 50
A8: Total HQLA | D8: =SUM(D3:D7) -> 1220
A10: Net Cash Outflows (30-day stress)
A11: Liability | B11: Amount | C11: Run-off Rate | D11: Cash Outflow
A12: Retail Deposits (Stable) | B12: =Inputs!B11 -> 1000 | C12: 0.05 | D12: =B12*C12 -> 50
A13: Retail Deposits (Less Stable) | B13: =Inputs!B12 -> 500 | C13: 0.1 | D13: =B13*C13 -> 50
A14: Wholesale Funding (<30 days) | B14: =Inputs!B13 -> 400 | C14: 0.25 | D14: =B14*C14 -> 100
A15: Interbank Loans (<30 days) | B15: =Inputs!B14 -> 200 | C15: 1 | D15: =B15*C15 -> 200
A16: Total Cash Outflows | D16: =SUM(D12:D15) -> 400
A18: LCR | D18: =D8/D16 -> 3.05
A19: Status | D19: =IF(D18>=1,"PASS","FAIL") -> PASS

Sheet NSFR
A1: Available Stable Funding (ASF)
A2: Funding Source | B2: Amount | C2: ASF Factor | D2: ASF Value
A3: Equity / Tier 1 Capital | B3: =Inputs!B15 -> 600 | C3: 1 | D3: =B3*C3 -> 600
A4: Retail Deposits (Stable) | B4: =Inputs!B11 -> 1000 | C4: 0.95 | D4: =B4*C4 -> 950
A5: Retail Deposits (Less Stable) | B5: =Inputs!B12 -> 500 | C5: 0.9 | D5: =B5*C5 -> 450
A6: Wholesale Funding (>1yr) | B6: =Inputs!B16 -> 300 | C6: 0.5 | D6: =B6*C6 -> 150
A7: Interbank (overnight) | B7: =Inputs!B14 -> 200 | C7: 0 | D7: =B7*C7 -> 0
A8: Total ASF | D8: =SUM(D3:D7) -> 2150
A10: Required Stable Funding (RSF)
A11: Asset | B11: Amount | C11: RSF Factor | D11: RSF Value
A12: Cash | B12: =Inputs!B2 -> 500 | C12: 0 | D12: =B12*C12 -> 0
A13: Government Bonds | B13: =Inputs!B4 -> 300 | C13: 0.05 | D13: =B13*C13 -> 15
A14: AAA Corporate Bonds | B14: =Inputs!B5 -> 200 | C14: 0.15 | D14: =B14*C14 -> 30
A15: Home Loans | B15: =Inputs!B7 -> 2000 | C15: 0.65 | D15: =B15*C15 -> 1300
A16: Corporate Loans | B16: =Inputs!B8 -> 800 | C16: 0.85 | D16: =B16*C16 -> 680
A17: Total RSF | D17: =SUM(D12:D16) -> 2025
A19: NSFR | D19: =D8/D17 -> 1.0617284
A20: Status | D20: =IF(D19>=1,"PASS","FAIL") -> PASS

Sheet Stress
A1: Stress Scenario Assumptions
A2: Scenario | B2: Retail Stable Run-off | C2: Retail Less Stable Run-off | D2: Wholesale Run-off | E2: Interbank Run-off
A3: Base Case | B3: 0.05 | C3: 0.1 | D3: 0.25 | E3: 1
A4: Mild Stress | B4: 0.08 | C4: 0.15 | D4: 0.35 | E4: 1
A5: Moderate Stress | B5: 0.12 | C5: 0.2 | D5: 0.5 | E5: 1
A6: Severe Stress | B6: 0.2 | C6: 0.3 | D6: 0.75 | E6: 1
A9: LCR Under Stress
A10: Scenario | B10: Total HQLA | C10: Total Outflows | D10: LCR | E10: Status
A11: Base Case | B11: =LCR!D8 -> 1220 | C11: =Inputs!B11*B3+Inputs!B12*C3+Inputs!B13*D3+Inputs!B14*E3 -> 400 | D11: =B11/C11 -> 3.05 | E11: =IF(D11>=1,"PASS","FAIL") -> PASS
A12: Mild Stress | B12: =LCR!D8 -> 1220 | C12: =Inputs!B11*B4+Inputs!B12*C4+Inputs!B13*D4+Inputs!B14*E4 -> 495 | D12: =B12/C12 -> 2.4646465 | E12: =IF(D12>=1,"PASS","FAIL") -> PASS
A13: Moderate Stress | B13: =LCR!D8 -> 1220 | C13: =Inputs!B11*B5+Inputs!B12*C5+Inputs!B13*D5+Inputs!B14*E5 -> 620 | D13: =B13/C13 -> 1.9677419 | E13: =IF(D13>=1,"PASS","FAIL") -> PASS
A14: Severe Stress | B14: =LCR!D8 -> 1220 | C14: =Inputs!B11*B6+Inputs!B12*C6+Inputs!B13*D6+Inputs!B14*E6 -> 850 | D14: =B14/C14 -> 1.4352941 | E14: =IF(D14>=1,"PASS","FAIL") -> PASS

Sheet Dashboard
A1: Basel III Liquidity Risk Dashboard
A3: Metric | B3: Value
A4: LCR (Base Case) | B4: =LCR!D18 -> 3.05
A5: LCR Status | B5: =LCR!D19 -> PASS
A6: NSFR | B6: =NSFR!D19 -> 1.0617284
A7: NSFR Status | B7: =NSFR!D20 -> PASS
A8: LCR — Mild Stress | B8: =Stress!D12 -> 2.4646465
A9: LCR — Moderate Stress | B9: =Stress!D13 -> 1.9677419
A10: LCR — Severe Stress | B10: =Stress!D14 -> 1.4352941
